ez_setup.py
setup.py
step1_unit_test.py
doc/conf.py
umi_tools/Documentation.py
umi_tools/Utilities.py
umi_tools/__init__.py
umi_tools/count.py
umi_tools/count_tab.py
umi_tools/dedup.py
umi_tools/extract.py
umi_tools/extract_methods.py
umi_tools/group.py
umi_tools/network.py
umi_tools/sam_methods.py
umi_tools/umi_methods.py
umi_tools/umi_tools.py
umi_tools/version.py
umi_tools/whitelist.py
umi_tools/whitelist_methods.py
umi_tools_csgx_b-1.1.1.dist-info/METADATA
umi_tools_csgx_b-1.1.1.dist-info/WHEEL
umi_tools_csgx_b-1.1.1.dist-info/licenses/LICENSE
umi_tools_csgx_b-1.1.1.dist-info/RECORD
