Metadata-Version: 2.1
Name: umi_tools_csgx_b
Version: 1.1.1
Summary: updated Vlad Kiselev umi-tools-csgx fork of umi-tools
Project-URL: Homepage, https://github.com/pmarafini/UMI-tools-csgx
Project-URL: Bug Tracker, https://github.com/pmarafini/UMI-tools-csgx/issues
Author-email: Pietro Marafini <marafini@csgenetics.com>
License-File: LICENSE
Classifier: License :: OSI Approved :: MIT License
Classifier: Operating System :: OS Independent
Classifier: Programming Language :: Python :: 3
Requires-Python: >=3.7
